<data>
	<easy>
		<patterns>		
			<pattern>
        <length>25</length>
				<spawn><distance>1</distance><object>Fly</object><ypos>1</ypos><parent>WaterSurface</parent></spawn>
        <spawn><distance>4</distance><object>Fly</object><ypos>2</ypos><parent>WaterSurface</parent></spawn>
        <spawn><distance>3</distance><object>Fly</object><ypos>3</ypos><parent>WaterSurface</parent></spawn>
			</pattern>

      <pattern>
        <length>24</length>
        <spawn>
          <distance>1</distance>
          <object>Fly</object>
          <ypos>1</ypos>
          <parent>WaterSurface</parent>
        </spawn>
      </pattern>
		</patterns>
	</easy>
	<medium>
		<patterns>
      <pattern>
        <length>25</length>
        <spawn><distance>1</distance><object>Fly</object><ypos>1</ypos><parent>WaterSurface</parent></spawn>
        <spawn><distance>2</distance><object>Fly</object><ypos>2</ypos><parent>WaterSurface</parent></spawn>
      </pattern>    
		</patterns>
	</medium>
	<hard>
		<patterns>
      <pattern>
        <length>25</length>
        <spawn><distance>1</distance><object>Fly</object><ypos>1</ypos><parent>WaterSurface</parent></spawn>
      </pattern>
		</patterns>
	</hard>
</data>